mtcli_book/__init__.py
mtcli_book/book.py
mtcli_book/conf.py
mtcli_book-0.2.3.dist-info/entry_points.txt
mtcli_book-0.2.3.dist-info/LICENSE
mtcli_book-0.2.3.dist-info/METADATA
mtcli_book-0.2.3.dist-info/WHEEL
mtcli_book-0.2.3.dist-info/RECORD
