Metadata-Version: 2.3
Name: mtcli-book
Version: 0.2.3
Summary: Plugin mtcli do book de ofertas
License: GPL-3.0
Author: Valmir França da Silva
Author-email: vfranca3@gmail.com
Requires-Python: >=3.11,<3.14.0
Classifier: License :: OSI Approved :: GNU General Public License v3 (GPLv3)
Classifier: Programming Language :: Python :: 3
Classifier: Programming Language :: Python :: 3.11
Classifier: Programming Language :: Python :: 3.12
Classifier: Programming Language :: Python :: 3.13
Requires-Dist: mtcli (>=1.18.1)
Requires-Dist: tabulate (>=0.9.0,<0.10.0)
Project-URL: Documentation, https://vfranca.github.io/mtcli-book
Project-URL: Homepage, https://github.com/vfranca/mtcli-book
Project-URL: Repository, https://github.com/vfranca/mtcli-book
Project-URL: issues, https://github.com/vfranca/mtcli-book/issues
